moru/__init__.py
moru/api/__init__.py
moru/api/client/__init__.py
moru/api/client/api/__init__.py
moru/api/client/api/sandboxes/__init__.py
moru/api/client/api/sandboxes/delete_sandboxes_sandbox_id.py
moru/api/client/api/sandboxes/get_sandboxes.py
moru/api/client/api/sandboxes/get_sandboxes_metrics.py
moru/api/client/api/sandboxes/get_sandboxes_sandbox_id.py
moru/api/client/api/sandboxes/get_sandboxes_sandbox_id_logs.py
moru/api/client/api/sandboxes/get_sandboxes_sandbox_id_metrics.py
moru/api/client/api/sandboxes/get_v2_sandboxes.py
moru/api/client/api/sandboxes/post_sandboxes.py
moru/api/client/api/sandboxes/post_sandboxes_sandbox_id_connect.py
moru/api/client/api/sandboxes/post_sandboxes_sandbox_id_pause.py
moru/api/client/api/sandboxes/post_sandboxes_sandbox_id_refreshes.py
moru/api/client/api/sandboxes/post_sandboxes_sandbox_id_resume.py
moru/api/client/api/sandboxes/post_sandboxes_sandbox_id_timeout.py
moru/api/client/api/templates/__init__.py
moru/api/client/api/templates/delete_templates_template_id.py
moru/api/client/api/templates/get_templates.py
moru/api/client/api/templates/get_templates_template_id.py
moru/api/client/api/templates/get_templates_template_id_builds_build_id_status.py
moru/api/client/api/templates/get_templates_template_id_files_hash.py
moru/api/client/api/templates/patch_templates_template_id.py
moru/api/client/api/templates/post_templates.py
moru/api/client/api/templates/post_templates_template_id.py
moru/api/client/api/templates/post_templates_template_id_builds_build_id.py
moru/api/client/api/templates/post_v2_templates.py
moru/api/client/api/templates/post_v3_templates.py
moru/api/client/api/templates/post_v_2_templates_template_id_builds_build_id.py
moru/api/client/client.py
moru/api/client/errors.py
moru/api/client/models/__init__.py
moru/api/client/models/aws_registry.py
moru/api/client/models/aws_registry_type.py
moru/api/client/models/build_log_entry.py
moru/api/client/models/build_status_reason.py
moru-0.1.0.dist-info/METADATA
moru-0.1.0.dist-info/WHEEL
moru-0.1.0.dist-info/licenses/LICENSE
moru-0.1.0.dist-info/RECORD
